<mxGraphModel style="default-style2"><root><mxCell id="0"/><mxCell id="1" parent="0"/><mxCell id="3" value="Modul" style="swimlane" parent="1" vertex="1"><mxGeometry x="210" y="140" width="520" height="273" as="geometry"/></mxCell><mxCell id="4" value="Sensor&#xa;(Device)" parent="3" vertex="1"><mxGeometry x="20" y="45" width="120" height="60" as="geometry"/></mxCell><mxCell id="5" value="Sensor&#xa;(Device)" parent="3" vertex="1"><mxGeometry x="20" y="135" width="120" height="60" as="geometry"/></mxCell><mxCell id="6" value="&#xa;uP" parent="3" vertex="1"><mxGeometry x="230" y="45" width="100" height="203" as="geometry"/></mxCell><mxCell id="10" value="" style="edgeStyle=elbowEdgeStyle;elbow=vertical;startArrow=classic" parent="3" source="6" target="4" edge="1"><mxGeometry width="100" height="100" as="geometry"><mxPoint y="100" as="sourcePoint"/><mxPoint x="100" as="targetPoint"/></mxGeometry></mxCell><mxCell id="11" value="" style="edgeStyle=elbowEdgeStyle;elbow=vertical;endArrow=classic;startArrow=classic" parent="3" source="6" target="5" edge="1"><mxGeometry width="100" height="100" as="geometry"><mxPoint y="100" as="sourcePoint"/><mxPoint x="100" as="targetPoint"/></mxGeometry></mxCell><mxCell id="12" value="Netzwerkcontroller" parent="3" vertex="1"><mxGeometry x="380" y="79" width="120" height="135" as="geometry"/></mxCell><mxCell id="14" value="" style="edgeStyle=elbowEdgeStyle;elbow=vertical;endArrow=classic;startArrow=classic" parent="3" source="12" target="6" edge="1"><mxGeometry width="100" height="100" as="geometry"><mxPoint y="100" as="sourcePoint"/><mxPoint x="100" as="targetPoint"/></mxGeometry></mxCell><mxCell id="16" value="SPI" style="text" parent="3" vertex="1"><mxGeometry x="343" y="125" width="80" height="20" as="geometry"/></mxCell><mxCell id="17" value="I2C, 1-Wire,..." style="text" parent="3" vertex="1"><mxGeometry x="142" y="48" width="80" height="20" as="geometry"/></mxCell><mxCell id="18" value="I2C, 1-Wire,..." style="text" parent="3" vertex="1"><mxGeometry x="142" y="139.5" width="80" height="20" as="geometry"/></mxCell><mxCell id="19" value="Netzwerk" style="ellipse;shape=cloud" parent="1" vertex="1"><mxGeometry x="750" y="246.5" width="120" height="80" as="geometry"/></mxCell><mxCell id="22" value="" style="edgeStyle=elbowEdgeStyle;elbow=vertical;startArrow=classic;endArrow=classic" parent="1" source="12" target="19" edge="1"><mxGeometry width="100" height="100" as="geometry"><mxPoint y="100" as="sourcePoint"/><mxPoint x="100" as="targetPoint"/></mxGeometry></mxCell><mxCell id="23" value="Ethernet/WLAN" style="text" parent="1" vertex="1"><mxGeometry x="750" y="226.5" width="80" height="20" as="geometry"/></mxCell></root></mxGraphModel>